MANIFEST.in
README.rst
setup.cfg
setup.py
versioneer.py
blueberrywsn/__init__.py
blueberrywsn/_version.py
blueberrywsn/constants.py
blueberrywsn/gui.py
blueberrywsn/pi.py
blueberrywsn/receiver.py
blueberrywsn/sensor.py
blueberrywsn/slice.py
blueberrywsn.egg-info/PKG-INFO
blueberrywsn.egg-info/SOURCES.txt
blueberrywsn.egg-info/dependency_links.txt
blueberrywsn.egg-info/entry_points.txt
blueberrywsn.egg-info/requires.txt
blueberrywsn.egg-info/top_level.txt