Metadata-Version: 1.1
Name: blueberrywsn
Version: 0.1.0
Summary: A Bluetooth wireless sensor network
Home-page: https://github.com/felipedau/blueberrywsn
Author: Felipe Dau
Author-email: dau.felipe@gmail.com
License: GPL
Keywords: bluetooth raspberry pi wireless sensor network
Platform: UNKNOWN
Classifier: Development Status :: 4 - Beta
Classifier: License :: OSI Approved :: GNU General Public License (GPL)
Classifier: Programming Language :: Python :: 2.7
